what_os/LICENSE
what_os/README.MD
what_os/__init__.py
what_os/requirements.txt
what_os/thirdparty.json
what_os-0.10.dist-info/LICENSE.rst
what_os-0.10.dist-info/METADATA
what_os-0.10.dist-info/WHEEL
what_os-0.10.dist-info/top_level.txt
what_os-0.10.dist-info/RECORD
